VisualMathematics/__init__.py
VisualMathematics-0.2.3.dist-info/LICENSE.txt
VisualMathematics-0.2.3.dist-info/METADATA
VisualMathematics-0.2.3.dist-info/WHEEL
VisualMathematics-0.2.3.dist-info/top_level.txt
VisualMathematics-0.2.3.dist-info/RECORD
