Metadata-Version: 2.1
Name: VisualMathematics
Version: 0.2.3
Summary: A python library to visualize mathematics
Author: Luka Dornbach
Author-email: lukadornbach@gmx.de
Classifier: Programming Language :: Python :: 3
Classifier: License :: OSI Approved :: MIT License
Classifier: Operating System :: OS Independent
License-File: LICENSE.txt
